<?xml version="1.0" encoding="UTF-8" standalone="yes"?>
<p:sld xmlns:a="http://schemas.openxmlformats.org/drawingml/2006/main" xmlns:r="http://schemas.openxmlformats.org/officeDocument/2006/relationships" xmlns:p="http://schemas.openxmlformats.org/presentationml/2006/main"><p:cSld><p:spTree><p:nvGrpSpPr><p:cNvPr id="1" name=""/><p:cNvGrpSpPr/><p:nvPr/></p:nvGrpSpPr><p:grpSpPr><a:xfrm><a:off x="0" y="0"/><a:ext cx="0" cy="0"/><a:chOff x="0" y="0"/><a:chExt cx="0" cy="0"/></a:xfrm></p:grpSpPr><p:sp><p:nvSpPr><p:cNvPr id="2" name="标题 1"/><p:cNvSpPr><a:spLocks noGrp="1"/></p:cNvSpPr><p:nvPr><p:ph type="title"/></p:nvPr></p:nvSpPr><p:spPr/><p:txBody><a:bodyPr/><a:lstStyle/><a:p><a:r><a:rPr lang="en-US" altLang="zh-CN" dirty="0" smtClean="0"/><a:t>Comparative advantage</a:t></a:r><a:endParaRPr lang="zh-CN" altLang="en-US" dirty="0"/></a:p></p:txBody></p:sp><p:sp><p:nvSpPr><p:cNvPr id="3" name="内容占位符 2"/><p:cNvSpPr><a:spLocks noGrp="1"/></p:cNvSpPr><p:nvPr><p:ph idx="1"/></p:nvPr></p:nvSpPr><p:spPr/><p:txBody><a:bodyPr><a:normAutofit fontScale="92500" lnSpcReduction="10000"/></a:bodyPr><a:lstStyle/><a:p><a:r><a:rPr lang="en-US" altLang="zh-CN" dirty="0" smtClean="0"/><a:t>Comparative advantage is an economic theory first developed by English economist David </a:t></a:r><a:r><a:rPr lang="en-US" altLang="zh-CN" dirty="0" err="1" smtClean="0"/><a:t>Richardo</a:t></a:r><a:r><a:rPr lang="en-US" altLang="zh-CN" dirty="0" smtClean="0"/><a:t>. According to this theory, a person has a comparative advantage at producing something if he can produce it at lower cost than anyone else. And having a comparative advantage is not the same as being the best at something. It can explain why a country might produce and export things that it doesn’t seem good at producing when compared directly to another country.</a:t></a:r><a:endParaRPr lang="zh-CN" altLang="en-US" dirty="0"/></a:p></p:txBody></p:sp></p:spTree></p:cSld><p:clrMapOvr><a:masterClrMapping/></p:clrMapOvr></p:sld>